vos_benchmark/__init__.py
vos_benchmark/benchmark.py
vos_benchmark/evaluator.py
vos_benchmark/utils.py
vos_benchmark-0.1.0.dist-info/METADATA
vos_benchmark-0.1.0.dist-info/WHEEL
vos_benchmark-0.1.0.dist-info/licenses/LICENSE
vos_benchmark-0.1.0.dist-info/licenses/LICENSE-DAVIS
vos_benchmark-0.1.0.dist-info/RECORD
