Metadata-Version: 2.1
Name: vos_benchmark
Version: 0.1.0
Summary: General multi-threaded benchmarking script for video object segmentation.
Project-URL: Homepage, https://github.com/hkchengrex/vos-benchmark
Project-URL: Bug Tracker, https://github.com/hkchengrex/vos-benchmark/issues
Author-email: Rex Cheng <hkchengrex@gmail.com>
License-File: LICENSE
License-File: LICENSE-DAVIS
Classifier: License :: OSI Approved :: MIT License
Classifier: Operating System :: OS Independent
Classifier: Programming Language :: Python :: 3
Requires-Python: >=3.7
Requires-Dist: numpy
Requires-Dist: opencv-python
Requires-Dist: pillow
Requires-Dist: scikit-image
Requires-Dist: tqdm
